algebra_with_sympy/__init__.py
algebra_with_sympy/algebraic_equation.py
algebra_with_sympy/preparser.py
algebra_with_sympy/version.py
algebra_with_sympy-1.1.3.dist-info/METADATA
algebra_with_sympy-1.1.3.dist-info/WHEEL
algebra_with_sympy-1.1.3.dist-info/top_level.txt
algebra_with_sympy-1.1.3.dist-info/RECORD
