Metadata-Version: 2.4
Name: Algebra_with_SymPy
Version: 1.1.3
Summary: Equations that can be algebraicly manipulated.
Author-email: Jonathan Gutow <gutow@uwosh.edu>
License-Expression: GPL-3.0+
Project-URL: Homepage, https://gutow.github.io/Algebra_with_Sympy/
Project-URL: Repository, https://github.com/gutow/Algebra_with_Sympy
Project-URL: Issues, https://github.com/gutow/Algebra_with_Sympy/issues
Keywords: symbolic algebra,computer algebra,CAS,calculations with units,sympy
Classifier: Development Status :: 5 - Production/Stable
Classifier: Intended Audience :: Developers
Classifier: Intended Audience :: Education
Classifier: Intended Audience :: End Users/Desktop
Classifier: Programming Language :: Python :: 3
Classifier: Operating System :: OS Independent
Requires-Dist: sympy-for-algebra~=1.13
